logflow/__init__.py
logflow/cli.py
logflow/config_handler.py
logflow/log_decorator.py
Logflow-0.0.1.dist-info/LICENSE
Logflow-0.0.1.dist-info/METADATA
Logflow-0.0.1.dist-info/WHEEL
Logflow-0.0.1.dist-info/entry_points.txt
Logflow-0.0.1.dist-info/top_level.txt
Logflow-0.0.1.dist-info/RECORD
