Metadata-Version: 2.1
Name: Logflow
Version: 0.0.1
Summary: A logging utility for data engineers
Home-page: https://github.com/libertyiskey/logflow
Author: libertyiskey
Author-email: your.email@example.com
License: MIT
Project-URL: Bug Tracker, https://github.com/libertyiskey/logflow/issues
Classifier: Programming Language :: Python :: 3
Classifier: License :: OSI Approved :: MIT License
Classifier: Operating System :: OS Independent
Requires-Python: >=3.6
License-File: LICENSE
